unpickle/__init__.py
unpickle/cli.py
unpickle/lightning.py
unpickle-0.1.1.dist-info/METADATA
unpickle-0.1.1.dist-info/WHEEL
unpickle-0.1.1.dist-info/entry_points.txt
unpickle-0.1.1.dist-info/RECORD
